buzz_client/__init__.py
buzz_client/cli.py
buzz_client/cli_parser.py
buzz_client/client.py
buzz_client-1.1.4.dist-info/METADATA
buzz_client-1.1.4.dist-info/WHEEL
buzz_client-1.1.4.dist-info/entry_points.txt
buzz_client-1.1.4.dist-info/RECORD
