Metadata-Version: 2.1
Name: buzz-client
Version: 1.1.4
Summary: A client for Buzz API
License: GPL
Author: Andrea Mistrali
Author-email: andrea@mistrali.pw
Requires-Python: >=3.10,<4.0
Classifier: License :: Other/Proprietary License
Classifier: Programming Language :: Python :: 3
Classifier: Programming Language :: Python :: 3.10
Classifier: Programming Language :: Python :: 3.11
Classifier: Programming Language :: Python :: 3.12
Requires-Dist: pyyaml (>=6.0.1,<7.0.0)
Requires-Dist: requests (>=2.31.0,<3.0.0)
Requires-Dist: scriptonite (>=1.0.3,<2.0.0)
